casepropods.dummy-0.2.4-py2.7-nspkg.pth
casepropods/dummy/__init__.py
casepropods/dummy/plugin.py
casepropods.dummy-0.2.4.dist-info/DESCRIPTION.rst
casepropods.dummy-0.2.4.dist-info/METADATA
casepropods.dummy-0.2.4.dist-info/RECORD
casepropods.dummy-0.2.4.dist-info/WHEEL
casepropods.dummy-0.2.4.dist-info/metadata.json
casepropods.dummy-0.2.4.dist-info/namespace_packages.txt
casepropods.dummy-0.2.4.dist-info/top_level.txt
